simple_http_checker/__init__.py
simple_http_checker/checker.py
simple_http_checker/cli.py
simple_http_checker-2.1.1.dist-info/licenses/LICENSE
simple_http_checker-2.1.1.dist-info/METADATA
simple_http_checker-2.1.1.dist-info/WHEEL
simple_http_checker-2.1.1.dist-info/entry_points.txt
simple_http_checker-2.1.1.dist-info/top_level.txt
simple_http_checker-2.1.1.dist-info/RECORD
