Metadata-Version: 2.4
Name: simple-http-checker
Version: 2.1.1
Summary: A simple CLI tool to check the status of URLs.
Requires-Python: >=3.9
License-File: LICENSE
Requires-Dist: requests<3.0,>=2.28
Requires-Dist: click<9.0,>=8.0
Provides-Extra: dev
Requires-Dist: pytest; extra == "dev"
Requires-Dist: pytest-mock; extra == "dev"
Requires-Dist: ruff; extra == "dev"
Requires-Dist: black; extra == "dev"
Requires-Dist: mypy; extra == "dev"
Requires-Dist: bandit; extra == "dev"
Requires-Dist: types-requests; extra == "dev"
Dynamic: license-file
